{
  "contracts": {
    "Liquidator": {
      "address": "0x90eD580c68d596069D66FbF589E12672D2F4F928",
      "constructorCode": "608060405234801561001057600080fd5b506131e2806100206000396000f3fe",
      "bodyBytecodeHash": "2e40613bce1ad99c059ca36794797dad1eb9f7bc12b6c5c1901d9e381816bf5e",
      "localBytecodeHash": "bc3f7f6288d9344c3658ef4465c4e5a1f930b082b1ede5385a72fb2dee8b9e6d",
      "deployedBytecodeHash": "bc3f7f6288d9344c3658ef4465c4e5a1f930b082b1ede5385a72fb2dee8b9e6d",
      "types": {
        "t_bool": {
          "id": "t_bool",
          "kind": "elementary",
          "label": "bool"
        },
        "t_uint256": {
          "id": "t_uint256",
          "kind": "elementary",
          "label": "uint256"
        },
        "t_array:50<t_uint256>": {
          "id": "t_array:50<t_uint256>",
          "valueType": "t_uint256",
          "length": "50",
          "kind": "array",
          "label": "uint256[50]"
        },
        "t_address": {
          "id": "t_address",
          "kind": "elementary",
          "label": "address"
        },
        "t_address_payable": {
          "id": "t_address_payable",
          "kind": "elementary",
          "label": "address payable"
        }
      },
      "storage": [
        {
          "contract": "Initializable",
          "path": "@openzeppelin/contracts-ethereum-package/contracts/Initializable.sol",
          "label": "initialized",
          "astId": 5,
          "type": "t_bool",
          "src": "757:24:0"
        },
        {
          "contract": "Initializable",
          "path": "@openzeppelin/contracts-ethereum-package/contracts/Initializable.sol",
          "label": "initializing",
          "astId": 8,
          "type": "t_bool",
          "src": "876:25:0"
        },
        {
          "contract": "Initializable",
          "path": "@openzeppelin/contracts-ethereum-package/contracts/Initializable.sol",
          "label": "______gap",
          "astId": 73,
          "type": "t_array:50<t_uint256>",
          "src": "1982:29:0"
        },
        {
          "contract": "FlashLoanReceiverBase",
          "path": "contracts/aave/FlashLoanReceiverBase.sol",
          "label": "addressesProvider",
          "astId": 1460,
          "type": "t_address",
          "src": "796:54:7"
        },
        {
          "contract": "Liquidator",
          "path": "contracts/Flashloan.sol",
          "label": "wallet",
          "astId": 829,
          "type": "t_address_payable",
          "src": "716:30:6"
        },
        {
          "contract": "Liquidator",
          "path": "contracts/Flashloan.sol",
          "label": "router",
          "astId": 831,
          "type": "t_address",
          "src": "752:32:6"
        }
      ],
      "warnings": {
        "hasConstructor": false,
        "hasSelfDestruct": false,
        "hasDelegateCall": false,
        "hasInitialValuesInDeclarations": false,
        "uninitializedBaseContracts": []
      }
    }
  },
  "solidityLibs": {},
  "proxies": {
    "Flash Loan Liquidation/Flashloan": [
      {
        "address": "0xb78D13E162B37271Cbe9bbE60AB55257B73F3bCC",
        "version": "1.0.0",
        "implementation": "0xe3b4aF8925909168A82C7e168b942FB015d72942",
        "admin": "0x553E9d99B258bE6173B09cE509FB40d4972dcb88",
        "kind": "Upgradeable"
      }
    ],
    "Flash Loan Liquidation/Liquidator": [
      {
        "address": "0x3C66B3435cd6A9AE33bD171e062574cCc4Fdb391",
        "version": "1.0.0",
        "implementation": "0x90eD580c68d596069D66FbF589E12672D2F4F928",
        "admin": "0x553E9d99B258bE6173B09cE509FB40d4972dcb88",
        "kind": "Upgradeable"
      }
    ]
  },
  "manifestVersion": "2.2",
  "version": "1.0.0",
  "dependencies": {
    "@openzeppelin/contracts-ethereum-package": {
      "package": "0x778dddF23Ec1B5Cb18394c6C110480CaaDB3B0f6",
      "version": "3.0.0"
    }
  },
  "proxyAdmin": {
    "address": "0x553E9d99B258bE6173B09cE509FB40d4972dcb88"
  }
}
